oom_reap_me_first/__init__.py
oom_reap_me_first/auto_enable.py
oom_reap_me_first-0.0.1.dist-info/LICENSE
oom_reap_me_first-0.0.1.dist-info/METADATA
oom_reap_me_first-0.0.1.dist-info/WHEEL
oom_reap_me_first-0.0.1.dist-info/top_level.txt
oom_reap_me_first-0.0.1.dist-info/RECORD
