Metadata-Version: 2.1
Name: oom-reap-me-first
Version: 0.0.1
Summary: Tool that tells your linux OS to kill this process first if you hit OOM.
Home-page: https://github.com/jbn/oom_reap_me_first
Author: "@generativist"
License: BSD 3-Clause License
Keywords: oom,swap space
Platform: UNKNOWN
Classifier: Programming Language :: Python :: 3
Classifier: License :: OSI Approved :: MIT License
Classifier: Operating System :: POSIX :: Linux
License-File: LICENSE
